odoo/addons/edi_exchange_template/README.rst
odoo/addons/edi_exchange_template/__init__.py
odoo/addons/edi_exchange_template/__manifest__.py
odoo/addons/edi_exchange_template/utils.py
odoo/addons/edi_exchange_template/components/__init__.py
odoo/addons/edi_exchange_template/components/common.py
odoo/addons/edi_exchange_template/components/output_mixin.py
odoo/addons/edi_exchange_template/i18n/edi_exchange_template.pot
odoo/addons/edi_exchange_template/models/__init__.py
odoo/addons/edi_exchange_template/models/edi_backend.py
odoo/addons/edi_exchange_template/models/edi_exchange_template_mixin.py
odoo/addons/edi_exchange_template/models/edi_exchange_template_output.py
odoo/addons/edi_exchange_template/readme/CONTRIBUTORS.rst
odoo/addons/edi_exchange_template/readme/DESCRIPTION.rst
odoo/addons/edi_exchange_template/security/ir_model_access.xml
odoo/addons/edi_exchange_template/static/description/icon.png
odoo/addons/edi_exchange_template/static/description/index.html
odoo/addons/edi_exchange_template/tests/__init__.py
odoo/addons/edi_exchange_template/tests/test_edi_backend_output.py
odoo/addons/edi_exchange_template/views/edi_exchange_template_output_views.xml
odoo13_addon_edi_exchange_template-13.0.1.7.2.dist-info/METADATA
odoo13_addon_edi_exchange_template-13.0.1.7.2.dist-info/WHEEL
odoo13_addon_edi_exchange_template-13.0.1.7.2.dist-info/top_level.txt
odoo13_addon_edi_exchange_template-13.0.1.7.2.dist-info/RECORD
